{
    "configurations": [
        {
            "name": "Win32",
            "includePath": [
                "${workspaceFolder}/**"
            ],
            "defines": [
                "_DEBUG",
                "UNICODE",
                "_UNICODE"
            ],
            "compilerPath": "E:\\data\\Fast-software\\MSYS2\\mingw64\\bin\\g++.exe",
            "cStandard": "c17",
            "cppStandard": "gnu++14",
            "intelliSenseMode": "gcc-x64"
        }
    ],
    "version": 4
}